cvtkit/__init__.py
cvtkit/camera.py
cvtkit/common.py
cvtkit/datasets/BaseDataset.py
cvtkit/datasets/__init__.py
cvtkit/datasets/dtu.py
cvtkit/filtering.py
cvtkit/geometry.py
cvtkit/io.py
cvtkit/metrics.py
cvtkit/visualization/__init__.py
cvtkit/visualization/latex.py
cvtkit/visualization/util.py
cvtkit/visualization/video.py
cvtkit-0.0.33.dist-info/LICENSE
cvtkit-0.0.33.dist-info/METADATA
cvtkit-0.0.33.dist-info/WHEEL
cvtkit-0.0.33.dist-info/RECORD
