Metadata-Version: 2.3
Name: cvtkit
Version: 0.0.33
Summary: A Python library including general functions and operations on various computer vision related structures.
License: GNU GENERAL PUBLIC LICENSE
Keywords: computer vision,3d reconstruction,geometry,machine learning
Author: Nathaniel Burgdorfer
Author-email: nburgdorfer@gmail.com
Requires-Python: >= 3.12
Classifier: Development Status :: 2 - Pre-Alpha
Classifier: Intended Audience :: Developers
Classifier: Intended Audience :: Education
Classifier: Intended Audience :: Science/Research
Classifier: License :: OSI Approved :: GNU General Public License v3 (GPLv3)
Classifier: Natural Language :: English
Classifier: Operating System :: OS Independent
Classifier: Programming Language :: Python :: 3
Classifier: Programming Language :: Python :: 3.12
Classifier: Topic :: Multimedia
Classifier: Topic :: Multimedia :: Graphics
Classifier: Topic :: Multimedia :: Graphics :: 3D Modeling
Classifier: Topic :: Multimedia :: Graphics :: 3D Rendering
Classifier: Topic :: Scientific/Engineering
Classifier: Topic :: Scientific/Engineering :: Image Processing
Classifier: Topic :: Scientific/Engineering :: Visualization
Classifier: Topic :: Utilities
Requires-Dist: matplotlib (>=3.10.1,<4.0.0)
Requires-Dist: numpy (>=2.1.2,<3.0.0)
Requires-Dist: open3d (>=0.19.0,<0.20.0)
Requires-Dist: opencv-python (>=4.11.0.86,<5.0.0.0)
Requires-Dist: scikit-image (>=0.25.2,<0.26.0)
Requires-Dist: scikit-learn (>=1.6.1,<2.0.0)
Requires-Dist: scipy (>=1.15.2,<2.0.0)
Requires-Dist: tqdm (>=4.67.1,<5.0.0)
Project-URL: Homepage, https://nburgdorfer.github.io/cvtkit/
Project-URL: Repository, https://github.com/nburgdorfer/cvtkit
